botframework/__init__.py
botframework/builder.py
botframework/cli.py
discordbotframework-0.1.3.dist-info/METADATA
discordbotframework-0.1.3.dist-info/WHEEL
discordbotframework-0.1.3.dist-info/entry_points.txt
discordbotframework-0.1.3.dist-info/top_level.txt
discordbotframework-0.1.3.dist-info/RECORD
