Metadata-Version: 2.4
Name: discordbotframework
Version: 0.1.3
Summary: Discord bot framework starter
Author: Your Name
License: MIT
Requires-Python: >=3.10
